sources/tektology/__init__.py
sources/tektology/definitions.py
tektology-0.0.0.dist-info/METADATA
tektology-0.0.0.dist-info/WHEEL
tektology-0.0.0.dist-info/licenses/LICENSE
tektology-0.0.0.dist-info/RECORD
