Metadata-Version: 2.1
Name: tektology
Version: 0.0.0
Summary: Compilation of many different design tools developed by the nkhklkstksch signature.
Project-URL: Homepage, https://nkhklkstksch.xyz
Author-email: nkhklkstksch <nkhklkstksch@icloud.com>
License-File: LICENSE
Classifier: License :: OSI Approved :: The Unlicense (Unlicense)
Classifier: Operating System :: OS Independent
Classifier: Programming Language :: Python :: 3
Classifier: Topic :: Scientific/Engineering
Requires-Python: >=3.10
